{
  "eden": [
    {
      "source_url": "https://github.com/eden-emulator/Releases/releases/download/v{VERSION}/*steamdeck-gcc-standard.AppImage",
      "source_type": "github_release",
      "version": "$EDEN_DESIRED_VERSION",
      "extraction_type": "appimage",
      "assets": [
        {
          "type": "dir",
          "source": "share",
          "dest": "share"
        },
        {
          "type": "dir",
          "source": "bin",
          "dest": "bin"
        },
        {
          "type": "dir",
          "source": "etc",
          "dest": "etc"
        },
        {
          "type": "dir",
          "source": "shared/bin",
          "dest": "bin"
        },
        {
          "type": "dir",
          "source": "$REPO_ROOT/$COMPONENT_NAME",
          "dest": "$COMPONENT_ARTIFACT_ROOT"
        },
        {
          "type": "create",
          "dest": "component_version",
          "contents": "$SOURCE_VERSION"
        },
        {
          "type": "file",
          "source": "$REPO_ROOT/$COMPONENT_NAME/component_functions.sh",
          "dest": "$COMPONENT_ARTIFACT_ROOT"
        },
        {
          "type": "file",
          "source": "$REPO_ROOT/$COMPONENT_NAME/component_launcher.sh",
          "dest": "$COMPONENT_ARTIFACT_ROOT"
        },
        {
          "type": "file",
          "source": "$REPO_ROOT/$COMPONENT_NAME/component_manifest.json",
          "dest": "$COMPONENT_ARTIFACT_ROOT"
        },
        {
          "type": "file",
          "source": "$REPO_ROOT/$COMPONENT_NAME/component_recipe.json",
          "dest": "$COMPONENT_ARTIFACT_ROOT"
        },
        {
          "type": "file",
          "source": "$REPO_ROOT/$COMPONENT_NAME/component_prepare.sh",
          "dest": "$COMPONENT_ARTIFACT_ROOT"
        },
        {
          "type": "file",
          "source": "$REPO_ROOT/$COMPONENT_NAME/component_update.sh",
          "dest": "$COMPONENT_ARTIFACT_ROOT"
        }
      ],
      "libs": [
        {
          "library": "libQt6Concurrent.so.6",
          "runtime_name": "org.kde.Platform",
          "runtime_version": "6.10",
          "dest": "shared-libs"
        },
        {
          "library": "libQt6Core.so.6",
          "runtime_name": "org.kde.Platform",
          "runtime_version": "6.10",
          "dest": "shared-libs"
        },
        {
          "library": "libQt6Widgets.so.6",
          "runtime_name": "org.kde.Platform",
          "runtime_version": "6.10",
          "dest": "shared-libs"
        },
        {
          "library": "libQt6Gui.so.6",
          "runtime_name": "org.kde.Platform",
          "runtime_version": "6.10",
          "dest": "shared-libs"
        },
        {
          "library": "libSPIRV-Tools-opt.so",
          "source": "lib",
          "dest": "shared-libs"
        },
        {
          "library": "libSPIRV-Tools.so",
          "source": "lib",
          "dest": "shared-libs"
        },
        {
          "library": "libSPIRV-Tools-link.so",
          "source": "lib",
          "dest": "shared-libs"
        },
        {
          "library": "libQt6DBus.so.6",
          "runtime_name": "org.kde.Platform",
          "runtime_version": "6.10",
          "dest": "shared-libs"
        },
        {
          "library": "libmbedtls.so.21",
          "source": "lib",
          "dest": "shared-libs"
        },
        {
          "library": "libmbedx509.so.7",
          "source": "lib",
          "dest": "shared-libs"
        },
        {
          "library": "libmbedcrypto.so.16",
          "source": "lib",
          "dest": "shared-libs"
        },
        {
          "library": "libenet.so.7",
          "source": "lib",
          "dest": "shared-libs"
        },
        {
          "library": "libboost_filesystem.so.1.89.0",
          "source": "lib",
          "dest": "shared-libs"
        },
        {
          "library": "libfmt.so.12",
          "source": "lib",
          "dest": "shared-libs"
        }
      ]
    }
  ]
}
