[
  {
    "library": "libslirp.so.0",
    "source": "xemu/usr/lib"
  },
  {
    "library": "libpcap.so.0.8",
    "source": "xemu/usr/lib"
  },
  {
    "library": "libcurl-gnutls.so.4",
    "source": "xemu/usr/lib"
  },
  {
    "library": "libkrb5.so.3",
    "source": "xemu/usr/lib"
  },
  {
    "library": "libgssapi_krb5.so.2",
    "source": "xemu/usr/lib"
  },
  {
    "library": "libkrb5support.so.0",
    "source": "xemu/usr/lib"
  },
  {
    "library": "librtmp.so.1",
    "source": "xemu/usr/lib"
  },
  {
    "library": "libssh.so.4",
    "source": "xemu/usr/lib"
  },
  {
    "library": "libk5crypto.so.3",
    "source": "xemu/usr/lib"
  },
  {
    "library": "liblber-2.5.so.0",
    "source": "xemu/usr/lib"
  },
  {
    "library": "libsasl2.so.2",
    "source": "xemu/usr/lib"
  },
  {
    "library": "libkeyutils.so.1",
    "source": "xemu/usr/lib"
  },
  {
    "library": "libldap-2.5.so.0",
    "source": "xemu/usr/lib"
  }
]






